Workbook

Sheet 目次
A1: CLUB GALAXY / Heaven's Garden POS
A2: 動作確認チェックリスト
A4: URL | B4: https://club-galaxy-frontend-g246er3f6q-an.a.run.app/
A5: ログイン | B5: owner/1234 (全権限) · staff/5678 (黒服) · cast1/1111 (キャスト)
A6: 所要時間 | B6: 全項目 約30分
A8: 使い方
A9: 1. 各シート(A〜L)をタブから開き、項目ごとに操作を実行
A10: 2. D列「結果」にプルダウンから OK / NG / 未実施 を選択
A11: 3. NG の場合は E列「備考」に不具合内容を記入 → 「不具合記録」シートに転記
A12: 4. シナリオシートで5本の通しテストも実施
A13: 5. 全項目OKとなったら先方に共有
A16: シート一覧と進捗
A17: シート | B17: 内容 | C17: 項目数 | D17: OK数 | E17: 進捗率
A18: A 料金体系 | B18: セット料金(内税)・値引き・シングルチャージ | C18: 8 | D18: =COUNTIF('A 料金体系'!D:D,"OK") | E18: =IFERROR(D18/C18,0)
A19: B 指名タイプ | B19: フリー/本指名/場内/同伴 選択、メニュー追加 | C19: 5 | D19: =COUNTIF('B 指名タイプ'!D:D,"OK") | E19: =IFERROR(D19/C19,0)
A20: C キャスト名付きメニュー | B20: 指名料/同伴/本カクがキャスト名付きで表示 | C20: 6 | D20: =COUNTIF('C キャスト名付きメニュー'!D:D,"OK") | E20: =IFERROR(D20/C20,0)
A21: D バック設定 | B21: キャスト単位のバック額編集 | C21: 8 | D21: =COUNTIF('D バック設定'!D:D,"OK") | E21: =IFERROR(D21/C21,0)
A22: E 給与計算 | B22: (時給+バック)×0.9 (指示書§4.1) | C22: 6 | D22: =COUNTIF('E 給与計算'!D:D,"OK") | E22: =IFERROR(D22/C22,0)
A23: F 伝票 | B23: 明細項目・複数客ケース | C23: 8 | D23: =COUNTIF('F 伝票'!D:D,"OK") | E23: =IFERROR(D23/C23,0)
A24: G 卓操作 | B24: 延長ダイアログ・微調整・取消 | C24: 10 | D24: =COUNTIF('G 卓操作'!D:D,"OK") | E24: =IFERROR(D24/C24,0)
A25: H 既存画面維持 | B25: 残り時間・セット数・ボタン群 | C25: 5 | D25: =COUNTIF('H 既存画面維持'!D:D,"OK") | E25: =IFERROR(D25/C25,0)
A26: I メニュー管理 | B26: カテゴリ別の登録・編集・削除 | C26: 6 | D26: =COUNTIF('I メニュー管理'!D:D,"OK") | E26: =IFERROR(D26/C26,0)
A27: J レポート | B27: カレンダー・推移・キャスト別 | C27: 7 | D27: =COUNTIF('J レポート'!D:D,"OK") | E27: =IFERROR(D27/C27,0)
A28: K エッジケース | B28: 同卓複合・値引き延長 | C28: 5 | D28: =COUNTIF('K エッジケース'!D:D,"OK") | E28: =IFERROR(D28/C28,0)
A29: L 法務税務 | B29: 内税表示・源泉税・月次CSV | C29: 4 | D29: =COUNTIF('L 法務税務'!D:D,"OK") | E29: =IFERROR(D29/C29,0)
A30: N シナリオ試験 | B30: 通しシナリオ5本 | C30: 26 | D30: =COUNTIF('N シナリオ試験'!D:D,"OK") | E30: =IFERROR(D30/C30,0)
A31: 合計 | C31: =SUM(C18:C30) | D31: =SUM(D18:D30) | E31: =IFERROR(D31/C31,0)
A33: 完了基準
A34: • 全項目OK(進捗率 100%)
A35: • N シナリオ試験 5本全通過
A36: • 不具合記録欄がすべて「修正済」

Sheet A 料金体系
A1: # | B1: 操作 | C1: 期待結果 | D1: 結果 | E1: 備考
A2: A-1 | B2: 空卓タップ → 時刻「20:30」で入店 | C2: 卓詳細のセット料金 ¥4,000
A3: A-2 | B3: 別卓で時刻「22:30」で入店 | C3: ¥5,000
A4: A-3 | B4: 別卓で時刻「00:30」で入店 | C4: ¥6,000
A5: A-4 | B5: 卓詳細 → セット料金値引きに「1000」入力 | C5: 表示が ¥4,000 → ¥3,000(値引¥1,000/セット)
A6: A-5 | B6: 値引きを「2000」に変更 | C6: 表示が ¥2,000 に
A7: A-6 | B7: 会計画面を開く | C7: TAX 20% が値引き後金額ベースで計算
A8: A-7 | B8: 1名入店 → 会計 | C8: 明細にシングルチャージ ¥2,000 が自動で入っている
A9: A-8 | B9: 2名入店 → 会計 | C9: シングルチャージは無い

Sheet B 指名タイプ
A1: # | B1: 操作 | C1: 期待結果 | D1: 結果 | E1: 備考
A2: B-1 | B2: 入店画面を開く | C2: 「フリー / 本指名 / 場内指名 / 同伴」4択表示
A3: B-3 | B3: フリー選択 → キャスト複数選択 → 入店 | C3: 卓詳細に「フリー」表示、注文一覧は空(シングルのみ)
A4: B-4 | B4: 本指名 + あいり選択 → 入店 | C4: 卓詳細「本指名」、注文一覧に「本指名あいり ¥1,500」
A5: B-5 | B5: 場内指名 + みく選択 → 入店 | C5: 注文一覧に「場内指名みく ¥500」
A6: B-6 | B6: 入店後、注文画面 → キャスト用タブ上部の「+ 同伴 ¥4,000」→ みく選択 | C6: 注文一覧に「同伴みく ¥4,000」追加

Sheet C キャスト名付きメニュー
A1: # | B1: 操作 | C1: 期待結果 | D1: 結果 | E1: 備考
A2: C-1 | B2: 本指名であいり・みく2名選択 → 入店 | C2: 「本指名あいり」「本指名みく」の2行自動追加
A3: C-2 | B3: 同伴で2名選択 → 入店 | C3: 「同伴あいり」「同伴みく」の2行自動追加
A4: C-3 | B4: 注文画面 → キャスト用 → 「レディースカクテル (本カク)」→ モーダルで「あいり」選択 | C4: 注文に「レディースカクテルあいり (本カク) ¥1,500」追加
A5: C-4 | B5: 会計画面の明細 | C5: 「本指名あいり ¥1,500」のようにキャスト名付きで表示
A6: C-5 | B6: C-2/C-3の注文 | C6: 同伴・本カクも同様にキャスト名付き
A7: C-6 | B7: 旧形式(「指名料 1,500円」単独行)が出ていないか | C7: そのような行は出ない

Sheet D バック設定
A1: # | B1: 操作 | C1: 期待結果 | D1: 結果 | E1: 備考
A2: D-1 | B2: 管理 → キャスト → あいり編集 → 本指名バック「1000」に変更 | C2: 給与画面で本指名カウント×¥1,000
A3: D-2 | B3: 「1500」に変更 | C3: バック¥1,500 反映
A4: D-3 | B4: 「0」に変更 | C4: バック¥0
A5: D-4 | B5: 場内指名バック「500」に変更 | C5: 給与画面で場内指名×¥500 反映
A6: D-5 | B6: 場内指名バック「0」に変更 | C6: バック¥0
A7: D-6 | B7: 本カクあいり × 2杯注文 → 給与画面確認 | C7: バック合計に ¥800 (400×2)
A8: D-7 | B8: 同伴 × 1回 → 給与画面 | C8: 同伴バック ¥4,000 反映
A9: D-8 | B9: 管理 → 料金 タブ → 本指名「1500 → 2000」に変更 | C9: キャストのバック設定は維持、新規注文は¥2,000

Sheet E 給与計算
A1: # | B1: 操作 | C1: 期待結果 | D1: 結果 | E1: 備考
A2: E-1 | B2: 給与画面の「税引前」= 時給1h(2,000) + 本指名(1,000) + 同伴(4,000) + 本カク1杯(400) | C2: ¥7,400
A3: E-2 | B3: 同上、ホステス税-10% 控除後「支給額」 | C3: ¥6,660
A4: E-3 | B4: 勤務時間4.5h × 時給2,000 | C4: 時給ベース ¥9,000 表示
A5: E-4 | B5: 本カク 0杯 | C5: 本カクバック行が ¥0 or 非表示
A6: E-5 | B6: 給与画面の「勤務実績」テーブル | C6: 日付/時間/日給/バック内訳/P合計/日給合計/ホステス税/総支給 が全列表示
A7: E-6 | B7: 月次合計(SalaryPage 下部 or 日経表PDF) | C7: 月合計が算出される

Sheet F 伝票
A1: # | B1: 操作 | C1: 期待結果 | D1: 結果 | E1: 備考
A2: F-1 | B2: セット3回分の卓を会計 | C2: 明細に「セット料金 ¥4,000 × 1名 × 3セット = ¥12,000」
A3: F-2 | B3: 1名卓を会計 | C3: シングルチャージ ¥2,000 行あり
A4: F-3 | B4: 本指名/場内/同伴/本カクのある卓を会計 | C4: 全てキャスト名付きで表示
A5: F-4 | B5: ドリンク/ボトル注文済みで会計 | C5: 各行に品名 x数量 ¥金額
A6: F-5 | B6: 「領収書」タブ | C6: 小計 / TAX 20% / 合計 / 卓番号 / 人数 / 担当 すべて表示
A7: F-6 | B7: みく本指名+同席計4名の卓 → 各自のフリードリンクを注文 | C7: 本指名は「みく」のみ、Fドリンクは castName 付きで各自分記録
A8: F-7 | B8: 同上で本カクみく × 2杯 | C8: 「レディースカクテルみく x2 ¥3,000」
A9: F-8 | B9: 同卓を会計完了 → 利益タブ → キャスト推移 → みく選択 | C9: 今月の売上に該当卓の小計が加算されている

Sheet G 卓操作
A1: # | B1: 操作 | C1: 期待結果 | D1: 結果 | E1: 備考
A2: G-1 | B2: 卓詳細ボタン | C2: 「延長 +30分」「延長 +60分」と明示
A3: G-2 | B3: 延長 +30分 タップ | C3: 確認ダイアログ「延長の確認」が開く
A4: G-3 | B4: ダイアログでキャンセル | C4: 延長されない・注文に延長料金行なし
A5: G-4 | B5: +30分 → 確定 | C5: 注文に「延長 +30分 ¥1,000」追加、残り時間 +30分
A6: G-5 | B6: +60分 → 確定 | C6: 注文に「延長 +60分 ¥3,000」追加、残り時間 +60分
A7: G-6 | B7: 卓詳細の延長履歴 → 「取消」タップ | C7: 延長注文が消え、残り時間も戻る
A8: G-7 | B8: +10分 タップ | C8: 残り時間 +10分、注文に変化なし
A9: G-8 | B9: -10分 タップ | C9: 残り時間 -10分、注文変化なし
A10: G-9 | B10: 延長ダイアログで指名「あいり」選択 → 確定 | C10: 延長¥1,000 の castName=あいり、あいりのバックに反映
A11: G-10 | B11: 誤タップ → 取消 → 再タップ → 確定 | C11: 二重課金にならず、正しい1回分のみ加算

Sheet H 既存画面維持
A1: # | B1: 操作 | C1: 期待結果 | D1: 結果 | E1: 備考
A2: H-1 | B2: フロア画面 | C2: 各使用中卓の右上に「残り N分」表示
A3: H-2 | B3: 卓詳細 | C3: 入店時刻・人数が表示
A4: H-3 | B4: 入店1時間以上放置 | C4: セット数が自動で増える(セット開始50分経過でアラート)
A5: H-4 | B5: 卓詳細の注文リスト | C5: 品名・数量・金額が全表示
A6: H-5 | B6: 卓詳細のボタン | C6: 「注文 / 会計 / チェック票 / 付け回し」全て動作

Sheet I メニュー管理
A1: # | B1: 操作 | C1: 期待結果 | D1: 結果 | E1: 備考
A2: I-1 | B2: 管理 → メニュー → ゲスト用メニューの種類 | C2: 焼酎/ウイスキー/ブランデー/シャンパン/ワイン/ゲストショット/ピッチャー/ゲストビール/割り物 すべて登録済み
A3: I-2 | B3: 「+追加」タップ | C3: 新規メニュー入力フォームが開く
A4: I-3 | B4: 既存メニューの「編集」タップ | C4: 価格・原価・バックを編集可能
A5: I-4 | B5: 既存メニューの「削除」タップ | C5: 確認ダイアログ → 削除
A6: I-5 | B6: キャスト用タブ → レディースカクテル選択時の動作(注文画面で) | C6: キャスト選択モーダルでキャスト選び → 本カクバックに反映
A7: I-6 | B7: 指示書§7.2のメニュー全70種 | C7: 注文画面のシャンパンにオーパスワン¥180,000、響12年¥350,000等が表示

Sheet J レポート
A1: # | B1: 操作 | C1: 期待結果 | D1: 結果 | E1: 備考
A2: J-1 | B2: 利益タブ → カレンダー タブ | C2: 月カレンダー上に各日の売上が小さく表示
A3: J-2 | B3: 日マスをタップ | C3: 下に内訳モーダル表示、担当キャスト別/卓別の明細
A4: J-3 | B4: 同上 | C4: 担当キャスト別にグループ化されている
A5: J-4 | B5: キャスト推移 タブ → あいり選択 | C5: 過去12ヶ月の売上グラフ表示
A6: J-5 | B6: 店舗推移 タブ → 過去12ヶ月 | C6: 月別の棒グラフ表示
A7: J-6 | B7: 同一日同一キャストの4卓 | C7: カレンダー日タップで4行、集計値が合う
A8: J-7 | B8: 本指名卓を会計 → キャスト推移 → 該当キャスト | C8: 卓の小計が売上に重畳加算されている

Sheet K エッジケース
A1: # | B1: 操作 | C1: 期待結果 | D1: 結果 | E1: 備考
A2: K-1 | B2: 本指名あいりの卓 → 途中で担当を「みく」に変更 | C2: 既存注文の「本指名あいり」はそのまま(バック帰属不変)
A3: K-2 | B3: 本指名あいり入店後、注文画面で「+ 同伴 ¥4,000」→ あいり選択 | C3: 「本指名あいり」+「同伴あいり」が両立
A4: K-3 | B4: セット値引き¥1,000 + 延長 +30分 | C4: セット料金は値引き後、延長¥1,000は値引きされず通常料金
A5: K-4 | B5: 管理で¥0メニュー作成 → 注文 | C5: 売上0/バック0で計上できる
A6: K-7 | B6: カード決済で会計 | C6: 明細に「カード」表記、税サ20%維持

Sheet L 法務税務
A1: # | B1: 操作 | C1: 期待結果 | D1: 結果 | E1: 備考
A2: L-1 | B2: 会計画面 | C2: 「セット料金(内税)」「注文小計(内税)」と内税明示
A3: L-2 | B3: 会計画面 | C3: TAX 20% が別行で外税として加算
A4: L-3 | B4: 給与画面 | C4: 「ホステス税(-10%)」行で控除額明記
A5: L-4 | B5: 管理 → 出力タブ → 月次税務集計CSV | C5: 売上・給与・源泉税・控除のCSVダウンロード

Sheet N シナリオ試験
A1: 受け入れテスト通しシナリオ
A3: # | B3: 手順 | C3: 期待結果 | D3: 結果 | E3: 備考
A4: シナリオ1: 1名様本指名客 (所要5分)
A5: 1-1 | B5: 21:30、空卓を選び「本指名 + あいり + 1名」で入店 | C5: 卓が使用中に、castNames=[あいり] で開始
A6: 1-2 | B6: 注文画面 → キャスト用 → レディースカクテル → あいり → 追加 | C6: 「レディースカクテルあいり (本カク) ¥1,500」追加
A7: 1-3 | B7: 注文画面 → ゲスト用 → ウイスキー(山崎)タップ → 追加 | C7: 「山崎 ¥60,000」追加
A8: 1-4 | B8: 22:00に経過 → セット2セット目に自動切替 | C8: setCount=2 に変化
A9: 1-5 | B9: 会計画面で確認: セット料金 + シングル + 本指名あいり + 本カクあいり + 山崎 + TAX20% | C9: 全項目表示、合計算出
A10: 1-6 | B10: 会計完了 → 利益タブ → キャスト推移 → あいり | C10: 売上に反映
A11: シナリオ2: 同伴+複数客 (所要7分)
A12: 2-1 | B12: 19:00、空卓を選び「同伴 + みく + 1名」で入店 | C12: 「同伴みく ¥4,000」注文に自動追加
A13: 2-2 | B13: 卓詳細で人数を4名に変更 (または新規注文画面から追加) | C13: guestCount=4
A14: 2-3 | B14: 注文画面 → 「+ 本指名 ¥1,500」チップ → みく選択 | C14: 「本指名みく ¥1,500」追加
A15: 2-4 | B15: キャスト用 → レディースカクテル → みく選択 → 2回タップ | C15: 「レディースカクテルみく x2 ¥3,000」
A16: 2-5 | B16: 卓詳細 → 延長 +60分 → ダイアログで指名「みく」→ 確定 | C16: 「延長 +60分 ¥3,000」追加、castName=みく
A17: 2-6 | B17: 会計画面で確認 | C17: 同伴みく/本指名みく/本カクみく/延長が並ぶ、シングルチャージなし
A18: 2-7 | B18: 会計完了 → 利益タブ → キャスト推移 → みく | C18: 売上に卓の小計が重畳加算
A19: シナリオ3: 押し間違いリカバリ (所要3分)
A20: 3-1 | B20: 適当な卓入店 → 延長 +60分 タップ → ダイアログでキャンセル | C20: 卓詳細変化なし(注文リストに延長なし)
A21: 3-2 | B21: 再度 延長 +30分 → 確定 | C21: 注文に「延長 +30分 ¥1,000」、残り時間 +30分
A22: 3-3 | B22: 延長履歴 → 取消タップ | C22: 注文から消える、残り時間 -30分
A23: 3-4 | B23: +10分 → 残り時間 +10分 | C23: 延長履歴は増えない
A24: 3-5 | B24: -10分 → 残り時間 -10分 | C24: 履歴変化なし
A25: シナリオ4: 値引き (所要3分)
A26: 4-1 | B26: 24時以降(ダミーで23:xxの近接時刻)の空卓に入店 | C26: セット料金 ¥6,000 表示
A27: 4-2 | B27: 値引き ¥1,000 入力 | C27: 表示が ¥5,000 に変化
A28: 4-3 | B28: 会計画面 | C28: 小計が ¥5,000 × 人数 × セット数で計算
A29: 4-4 | B29: TAX 20%確認 | C29: 値引き後金額ベース
A30: シナリオ5: 月次給与 (所要5分)
A31: 5-1 | B31: 管理 → 出力 タブ → 「月次税務集計CSV」 | C31: 対象月指定可能
A32: 5-2 | B32: CSV ダウンロード → Excelで開く | C32: 各キャストの給与内訳が揃う
A33: 5-3 | B33: 給与ページ → あいり → 日経表PDF出力 | C33: ブラウザ印刷ダイアログが開く
A34: 5-4 | B34: PDFに保存 → 内容確認 | C34: 日付/時間/日給/バック内訳/P合計/税/総支給 が記載

Sheet 不具合記録
A1: 不具合記録
A3: # | B3: 発生日時 | C3: 画面 | D3: 症状 | E3: 再現手順 | F3: 修正済
